import_tracker/__init__.py
import_tracker/__main__.py
import_tracker/constants.py
import_tracker/import_tracker.py
import_tracker/lazy_import_errors.py
import_tracker/log.py
import_tracker/setup_tools.py
import_tracker-3.2.1.dist-info/LICENSE
import_tracker-3.2.1.dist-info/METADATA
import_tracker-3.2.1.dist-info/WHEEL
import_tracker-3.2.1.dist-info/top_level.txt
import_tracker-3.2.1.dist-info/RECORD
