Metadata-Version: 2.1
Name: import-tracker
Version: 3.2.1
Summary: A tool for managing dependencies in a modular python project by tracking which dependencies are needed by which sub-modules
Home-page: https://github.com/IBM/import-tracker
Author: Gabe Goodhart
Author-email: gabe.l.hart@gmail.com
License: MIT
Keywords: import,importlib,dependencies
Platform: UNKNOWN
Classifier: Intended Audience :: Developers
Classifier: Programming Language :: Python :: 3
Classifier: Programming Language :: Python :: 3.7
Classifier: Programming Language :: Python :: 3.8
Classifier: Programming Language :: Python :: 3.9
Classifier: Programming Language :: Python :: 3.10
Classifier: Programming Language :: Python :: 3.11
Classifier: Programming Language :: Python :: 3.12
License-File: LICENSE
